{
  "JsonPreguntas": [
    {
      "NumPregunta": 1,
      "pregunta": "¿Cual es tu sexo?",
      "Respuesta1": "Hombre",
      "opcion1": 11,
      "Respuesta2": "Mujer",
      "opcion2": 11,
      "Respuesta3": "",
      "opcion3": 0,
      "Respuesta4": "",
      "opcion4": 0
    },{
      "NumPregunta": 12,
      "pregunta": "¿Padeces de alguna enfermedad que pueda dificultar tu entrenamiento?",
      "Respuesta1": "Si",
      "opcion1": 1,
      "Respuesta2": "No",
      "opcion2": 13,
      "Respuesta3": "",
      "opcion3": 0,
      "Respuesta4": "",
      "opcion4": 0
    },
    {
      "NumPregunta": 13,
      "pregunta": "¿Esta enfermedad te imposibilita entrenar totalmente algun grupo muscular?",
      "Respuesta1": "Si",
      "opcion1": 1,
      "Respuesta2": "No",
      "opcion2": 12,
      "Respuesta3": "",
      "opcion3": 0,
      "Respuesta4": "",
      "opcion4": 0
    },{
      "NumPregunta": 14,
      "pregunta": "¿Que te dificulta esta enfermedad?",
      "Respuesta1": "Ejercicios de tren superior",
      "opcion1": 11,
      "Respuesta2": "Ejercicios de tren inferior",
      "opcion2": 11,
      "Respuesta3": "Ejercicios cardiovasculares",
      "opcion3": 11,
      "Respuesta4": "TODOS",
      "opcion4": 11
    },

    {
      "NumPregunta": 25,
      "pregunta": "¿Tienes alguna lesion que te afecte en tu entrenamiento?",
      "Respuesta1": "Si",
      "opcion1": 1,
      "Respuesta2": "No",
      "opcion2": 14,
      "Respuesta3": "",
      "opcion3": 0,
      "Respuesta4": "",
      "opcion4": 0
    },{
      "NumPregunta": 26,
      "pregunta": "¿En que tren te afecta esta lesion?",
      "Respuesta1": "Tren superior",
      "opcion1": 2,
      "Respuesta2": "Tren inferior",
      "opcion2": 1,
      "Respuesta3": "",
      "opcion3": 0,
      "Respuesta4": "",
      "opcion4": 0
    },
    {
      "NumPregunta": 27,
      "pregunta": "¿En que parte es esta lesion?",
      "Respuesta1": "Rodilla",
      "opcion1": 12,
      "Respuesta2": "Tobillo",
      "opcion2": 12,
      "Respuesta3": "Isquios",
      "opcion3": 12,
      "Respuesta4": "Cuadriceps",
      "opcion4": 12
    },
    {
      "NumPregunta": 28,
      "pregunta": "¿En que parte es esta lesion?",
      "Respuesta1": "Hombro",
      "opcion1": 11,
      "Respuesta2": "Pecho",
      "opcion2": 11,
      "Respuesta3": "Brazo",
      "opcion3": 11,
      "Respuesta4": "Espalda",
      "opcion4": 11
    },
    {
      "NumPregunta": 39,
      "pregunta": "¿Cual es tu experiencia en el gimnasio?",
      "Respuesta1": "Novato",
      "opcion1": 1,
      "Respuesta2": "Intermedio",
      "opcion2": 1,
      "Respuesta3": "Avanzado",
      "opcion3": 1,
      "Respuesta4": "",
      "opcion4": 0
    },
    {
      "NumPregunta":40,
      "pregunta": "¿Cuál es su nivel de condición física actual?",
      "Respuesta1": "Bajo",
      "opcion1": 1,
      "Respuesta2": "Mediano o alto",
      "opcion2": 1,
      "Respuesta3": "",
      "opcion3": 0,
      "Respuesta4": "",
      "opcion4": 0
    },
    {
      "NumPregunta": 41,
      "pregunta": "¿Cuantos dias entrenas?",
      "Respuesta1": "3",
      "opcion1": 1,
      "Respuesta2": "5",
      "opcion2": 1,
      "Respuesta3": "6",
        "opcion3": 1,
      "Respuesta4": "",
      "opcion4": 0
    },
    {
      "NumPregunta": 42,
      "pregunta": "¿Dispones del mismo tiempo todos los dias?",
      "Respuesta1": "Si",
      "opcion1": 1,
      "Respuesta2": "No",
      "opcion2": 2,
      "Respuesta3": "",
      "opcion3": 0,
      "Respuesta4": "",
      "opcion4": 0
    },{
      "NumPregunta": 43,
      "pregunta": "¿Con cuanto tiempo dispones  para hacer ejercicio?",
      "Respuesta1": "Menos de 60 mins",
      "opcion1": 13,
      "Respuesta2": "Entre 60 y 90 mins",
      "opcion2": 13,
      "Respuesta3": "Más de 90 mins",
      "opcion3": 13,
      "Respuesta4": "",
      "opcion4": 0
    },{
      "NumPregunta": 44,
      "pregunta": "Cuanto tiempo tienes para entrenar el dia ",
      "Respuesta1": "Menos de 60 minutos",
      "opcion1": 12,
      "Respuesta2": "Entre 60 y 90 minutos",
      "opcion2": 12,
      "Respuesta3": "Mas de 90 minutos",
      "opcion3": 12,
      "Respuesta4": "",
      "opcion4": 0
    },{
      "NumPregunta": 56,
        "pregunta": "¿Cuál es su objetivo principal de entrenamiento?",
        "Respuesta1": " Ganar masa muscular",
        "opcion1": 1,
        "Respuesta2": "Ganar Fuerza",
        "opcion2": 1,
        "Respuesta3": "Bajar de peso",
        "opcion3": 1,
        "Respuesta4": "Mantener la forma física actual",
      "opcion4":1
      },{
      "NumPregunta": 57,
        "pregunta": "¿En qué músculos desea enfocarse?",
        "Respuesta1": "Tren Superior",
        "opcion1": 1,
        "Respuesta2": "Tren Inferior",
        "opcion2": 1,
        "Respuesta3": "Cuerpo completo",
        "opcion3": 1,
      "Respuesta4": "",
      "opcion4":0
    },{
      "NumPregunta": 58,
      "pregunta": "¿Desea agregar abdomen a su rutina?",
      "Respuesta1": "Si",
      "opcion1": 11,
      "Respuesta2": "No",
      "opcion2": 11,
      "Respuesta3": "",
      "opcion3": 0,
      "Respuesta4": "",
      "opcion4":0
    },{
        "NumPregunta": 69,
            "pregunta": "¿Que equipo preferirias usar a la hora de entrenar?",
            "Respuesta1": "Mancuernas",
            "opcion1": 1,
            "Respuesta2": "Poleas",
            "opcion2": 1,
            "Respuesta3": "Barras",
            "opcion3": 1,
            "Respuesta4": "Maquinas",
            "opcion4": 1
        }
  ]
}